webview/__init__.py
webview/webview.py
webview_android-0.10.dist-info/LICENSE
webview_android-0.10.dist-info/METADATA
webview_android-0.10.dist-info/WHEEL
webview_android-0.10.dist-info/top_level.txt
webview_android-0.10.dist-info/RECORD
