Metadata-Version: 2.1
Name: webview-android
Version: 0.10
Summary: Simple WebView for android with python
Home-page: UNKNOWN
Author: Edilson Pineda
Author-email: edilsonpineda011@gmail.com
License: UNKNOWN
Keywords: webview android kivy kivymd Android WebView python-for-android python
Platform: UNKNOWN
Classifier: Programming Language :: Python :: 3
Classifier: License :: OSI Approved :: MIT License
Classifier: Operating System :: Android
Requires-Python: >=3
Requires-Dist: pyjnius
